reahl/ptongue/__init__.py
reahl/ptongue/gemproxy.py
reahl/ptongue/gemproxylinked.py
reahl/ptongue/gemproxyrpc.py
reahl/ptongue/gemstone.py
reahl/ptongue/gemstonecontrol.py
reahl_parseltongue-3.0.0.dist-info/licenses/COPYING
reahl_parseltongue-3.0.0.dist-info/licenses/COPYING.LESSER
reahl_parseltongue-3.0.0.dist-info/METADATA
reahl_parseltongue-3.0.0.dist-info/WHEEL
reahl_parseltongue-3.0.0.dist-info/top_level.txt
reahl_parseltongue-3.0.0.dist-info/RECORD
