Metadata-Version: 2.4
Name: reahl-parseltongue
Version: 3.0.0
Summary: Python bindings for GemStone/S 64 Bit
Author-email: Iwan Vosloo <iwan@reahl.org>, Craig Sparks <craig@reahl.org>
License: LGPL-3.0-or-later
License-File: COPYING
License-File: COPYING.LESSER
Requires-Dist: reahl-component
Requires-Dist: packaging
Provides-Extra: test
Requires-Dist: pytest; extra == "test"
Requires-Dist: reahl-component; extra == "test"
Requires-Dist: reahl-tofu; extra == "test"
Provides-Extra: docs
Requires-Dist: sphinx>=5.0.0; extra == "docs"
Requires-Dist: sphinx-rtd-theme>=1.0.0; extra == "docs"
Requires-Dist: sphinxcontrib-apidoc>=0.3.0; extra == "docs"
Dynamic: license-file
